[
{
	"url":"img/01-06-47-4017-iq5shj-1900001.jpg",
	"title":"石牛",
	"description":"石牛食品始创于1990年，专注于休闲食品二十余年，是西南地区规模较大、品种齐全的糖"
},
{
	"url":"img/01-06-46-4016-0tyo8n-1900001.png",
	"title":"埃锐",
	"description":"石牛食品始创于1990年，专注于休闲食品二十余年，是西南地区规模较大、品种齐全的糖"
},
{
	"url":"img/01-06-45-4015-i9e6co-1900001.jpg",
	"title":"LCN乾德",
	"description":"石牛食品始创于1990年，专注于休闲食品二十余年，是西南地区规模较大、品种齐全的糖"
},
{
	"url":"img/01-06-44-4014-lietxx-1900001.jpg",
	"title":"温州胜国",
	"description":"石牛食品始创于1990年，专注于休闲食品二十余年，是西南地区规模较大、品种齐全的糖"
},
{
	"url":"img/01-06-47-4017-iq5shj-1900001.jpg",
	"title":"石牛",
	"description":"石牛食品始创于1990年，专注于休闲食品二十余年，是西南地区规模较大、品种齐全的糖"
},
{
	"url":"img/01-06-47-4017-iq5shj-1900001.jpg",
	"title":"石牛",
	"description":"石牛食品始创于1990年，专注于休闲食品二十余年，是西南地区规模较大、品种齐全的糖"
},
{
	"url":"img/01-06-47-4017-iq5shj-1900001.jpg",
	"title":"石牛",
	"description":"石牛食品始创于1990年，专注于休闲食品二十余年，是西南地区规模较大、品种齐全的糖"
},
{
	"url":"img/01-06-47-4017-iq5shj-1900001.jpg",
	"title":"石牛",
	"description":"石牛食品始创于1990年，专注于休闲食品二十余年，是西南地区规模较大、品种齐全的糖"
},
{
	"url":"img/01-06-47-4017-iq5shj-1900001.jpg",
	"title":"石牛",
	"description":"石牛食品始创于1990年，专注于休闲食品二十余年，是西南地区规模较大、品种齐全的糖"
}
]